drf_request_client/VERSION
drf_request_client/__init__.py
drf_request_client/drf_request_client.py
drf_request_client-2.1.1.dist-info/LICENCE.txt
drf_request_client-2.1.1.dist-info/METADATA
drf_request_client-2.1.1.dist-info/WHEEL
drf_request_client-2.1.1.dist-info/top_level.txt
drf_request_client-2.1.1.dist-info/RECORD
