Metadata-Version: 2.1
Name: drf-request-client
Version: 2.1.1
Summary: Client wrapper for a DRF
Home-page: https://aerobotics.com
Author: Aerobotics
Author-email: adam@aerobotics.com
License: UNKNOWN
Keywords: api request django rest framework
Platform: UNKNOWN
Classifier: Development Status :: 4 - Beta
Classifier: Intended Audience :: Developers
Classifier: Topic :: Software Development :: Build Tools
Classifier: License :: OSI Approved :: Apache Software License
Classifier: Programming Language :: Python :: 3
Requires-Python: >=3.5
Requires-Dist: urllib3 (~=1.22)
Requires-Dist: requests (<3.0.0,>=2.18.4)
